Workbook

Sheet Checklist
A1: Section | B1: ID | C1: Test Case | D1: Expected Result | E1: Pass/Fail | F1: Notes
A2: 1. Installation | B2: INST-01 | C2: Sideload canonical APK via file transfer 1. Copy auvora-wallet-1.0.0-alpha.1-arm64.apk from dist folder to phone. 2. Open file in Files/Chrome; allow Install unknown apps if prompted. 3. Confirm package installer. | D2: Installer shows Auvora Wallet / com.auvora.auvora_wallet. Install completes without package parse errors. App icon appears in launcher.
A3: 1. Installation | B3: INST-02 | C3: Install via ADB (USB debugging) 1. Enable Developer options + USB debugging. 2. adb devices shows device authorized. 3. adb install -r the dist APK path. | D3: adb reports Success. Package com.auvora.auvora_wallet is installed/updated.
A4: 1. Installation | B4: INST-03 | C4: Confirm versionName and versionCode 1. After install, run dumpsys package filter for versionName/versionCode OR open in-app About. | D4: versionName=1.0.0-alpha.1 and versionCode=5. About shows Version 1.0 Alpha / 1.0.0-alpha.1 / channel alpha.
A5: 1. Installation | B5: INST-04 | C5: Cold launch after install 1. Force-stop if needed; tap app icon from launcher. 2. Observe splash → first screen. | D5: App launches to splash then onboarding or unlock without crash. No immediate ANR dialog.
A6: 1. Installation | B6: INST-05 | C6: Debug-signing awareness 1. Note any Play Protect / unknown-developer warnings during or after install. 2. Confirm install still proceeds when user accepts. | D6: Debug-signed APK may trigger warnings (expected for Alpha; no upload keystore). Warnings do not prevent install on tester device after user consent.
A7: 1. Installation | B7: INST-06 | C7: arm64 device compatibility gate 1. Confirm device CPU is arm64-v8a (About phone / adb getprop ro.product.cpu.abi). 2. Install and launch. | D7: App runs on arm64. Do not Pass on 32-bit-only devices — Flutter runtime is arm64-only in this APK (other ABI folders lack libflutter.so).
A8: 1. Installation | B8: INST-07 | C8: minSdk / OS floor 1. Confirm Android version ≥ 7.0 (API 24). 2. Attempt install on supported device. | D8: Install succeeds on API 24+. Package declares minSdk 24 / targetSdk 36.
A9: 1. Installation | B9: INST-08 | C9: Reinstall / upgrade path 1. Install APK once; create a throwaway wallet if prompted. 2. adb install -r same APK again. 3. Relaunch. | D9: Upgrade install succeeds. App opens without wipe unless user cleared data. No duplicate-package conflict.
A10: 1. Installation | B10: INST-09 | C10: Uninstall hygiene 1. Uninstall from system settings. 2. Confirm package gone (adb shell pm list packages | findstr auvora). | D10: Package removed. Reinstall presents fresh onboarding (local wallet data cleared with uninstall).
A11: 2. Onboarding | B11: ONB-01 | C11: First-run welcome / intro 1. Fresh install; launch app. 2. Walk through any intro / welcome screens. | D11: Onboarding screens render; CTAs for Create and Import (or equivalent) are visible and tappable. No blank/frozen first frame after splash.
A12: 2. Onboarding | B12: ONB-02 | C12: Alpha honesty messaging early 1. During onboarding or About accessible from early flow, look for Alpha / funding / preview messaging. | D12: User can discover that this is Version 1.0 Alpha with locked funding / preview transfers (About and/or banners). Copy does not claim live production funding.
A13: 2. Onboarding | B13: ONB-03 | C13: Create vs Import entry points 1. From onboarding home, tap Create wallet path then back. 2. Tap Import / Restore path then back. | D13: Both journeys are reachable; Back returns without corrupting first-run state.
... A128: 25. Crash Recovery | B128: CR-04 | C128: Low-memory reclaim smoke 1. Open Auvora; switch to heavy apps to encourage reclaim. 2. Return via recents or launcher. | D128: Either restores UI state or cleanly re-locks and reloads. No crash loop on resume.

Sheet Sign-off
A1: Version 1.0 Alpha Manual Test Sign-off
A3: Field | B3: Value
A4: Product | B4: Auvora Wallet
A5: Package | B5: com.auvora.auvora_wallet
A6: Version | B6: 1.0.0-alpha.1
A7: versionCode | B7: 5
A8: APK path | B8: D:\auvora-build\dist\alpha-1.0.0\auvora-wallet-1.0.0-alpha.1-arm64.apk
A9: APK SHA-256 | B9: b6aeb67f1bf3f41f4c2b9be90462236277d15d812f988e40d2bdc6875cd087e9
A10: Checklist date | B10: 2026-07-31
A11: Tester
A12: Device model
A13: Android version
A14: Test date
A15: Build hash / APK filename
A16: Overall result
A17: Critical blockers (Y/N + IDs)
A18: Notes / acknowledgement

Sheet Summary
A1: Section | B1: Total | C1: Pass | D1: Fail | E1: Blocked | F1: N/A | G1: Blank
A2: 1. Installation | B2: =COUNTIF(Checklist!A:A,A2) | C2: =COUNTIFS(Checklist!A:A,A2,Checklist!E:E,"Pass") | D2: =COUNTIFS(Checklist!A:A,A2,Checklist!E:E,"Fail") | E2: =COUNTIFS(Checklist!A:A,A2,Checklist!E:E,"Blocked") | F2: =COUNTIFS(Checklist!A:A,A2,Checklist!E:E,"N/A") | G2: =COUNTIFS(Checklist!A:A,A2,Checklist!E:E,"")
A3: 2. Onboarding | B3: =COUNTIF(Checklist!A:A,A3) | C3: =COUNTIFS(Checklist!A:A,A3,Checklist!E:E,"Pass") | D3: =COUNTIFS(Checklist!A:A,A3,Checklist!E:E,"Fail") | E3: =COUNTIFS(Checklist!A:A,A3,Checklist!E:E,"Blocked") | F3: =COUNTIFS(Checklist!A:A,A3,Checklist!E:E,"N/A") | G3: =COUNTIFS(Checklist!A:A,A3,Checklist!E:E,"")
A4: 3. Wallet Creation | B4: =COUNTIF(Checklist!A:A,A4) | C4: =COUNTIFS(Checklist!A:A,A4,Checklist!E:E,"Pass") | D4: =COUNTIFS(Checklist!A:A,A4,Checklist!E:E,"Fail") | E4: =COUNTIFS(Checklist!A:A,A4,Checklist!E:E,"Blocked") | F4: =COUNTIFS(Checklist!A:A,A4,Checklist!E:E,"N/A") | G4: =COUNTIFS(Checklist!A:A,A4,Checklist!E:E,"")
A5: 4. Wallet Import | B5: =COUNTIF(Checklist!A:A,A5) | C5: =COUNTIFS(Checklist!A:A,A5,Checklist!E:E,"Pass") | D5: =COUNTIFS(Checklist!A:A,A5,Checklist!E:E,"Fail") | E5: =COUNTIFS(Checklist!A:A,A5,Checklist!E:E,"Blocked") | F5: =COUNTIFS(Checklist!A:A,A5,Checklist!E:E,"N/A") | G5: =COUNTIFS(Checklist!A:A,A5,Checklist!E:E,"")
A6: 5. Portfolio | B6: =COUNTIF(Checklist!A:A,A6) | C6: =COUNTIFS(Checklist!A:A,A6,Checklist!E:E,"Pass") | D6: =COUNTIFS(Checklist!A:A,A6,Checklist!E:E,"Fail") | E6: =COUNTIFS(Checklist!A:A,A6,Checklist!E:E,"Blocked") | F6: =COUNTIFS(Checklist!A:A,A6,Checklist!E:E,"N/A") | G6: =COUNTIFS(Checklist!A:A,A6,Checklist!E:E,"")
A7: 6. Asset Details | B7: =COUNTIF(Checklist!A:A,A7) | C7: =COUNTIFS(Checklist!A:A,A7,Checklist!E:E,"Pass") | D7: =COUNTIFS(Checklist!A:A,A7,Checklist!E:E,"Fail") | E7: =COUNTIFS(Checklist!A:A,A7,Checklist!E:E,"Blocked") | F7: =COUNTIFS(Checklist!A:A,A7,Checklist!E:E,"N/A") | G7: =COUNTIFS(Checklist!A:A,A7,Checklist!E:E,"")
A8: 7. Send | B8: =COUNTIF(Checklist!A:A,A8) | C8: =COUNTIFS(Checklist!A:A,A8,Checklist!E:E,"Pass") | D8: =COUNTIFS(Checklist!A:A,A8,Checklist!E:E,"Fail") | E8: =COUNTIFS(Checklist!A:A,A8,Checklist!E:E,"Blocked") | F8: =COUNTIFS(Checklist!A:A,A8,Checklist!E:E,"N/A") | G8: =COUNTIFS(Checklist!A:A,A8,Checklist!E:E,"")
A9: 8. Receive | B9: =COUNTIF(Checklist!A:A,A9) | C9: =COUNTIFS(Checklist!A:A,A9,Checklist!E:E,"Pass") | D9: =COUNTIFS(Checklist!A:A,A9,Checklist!E:E,"Fail") | E9: =COUNTIFS(Checklist!A:A,A9,Checklist!E:E,"Blocked") | F9: =COUNTIFS(Checklist!A:A,A9,Checklist!E:E,"N/A") | G9: =COUNTIFS(Checklist!A:A,A9,Checklist!E:E,"")
A10: 9. QR Scanner | B10: =COUNTIF(Checklist!A:A,A10) | C10: =COUNTIFS(Checklist!A:A,A10,Checklist!E:E,"Pass") | D10: =COUNTIFS(Checklist!A:A,A10,Checklist!E:E,"Fail") | E10: =COUNTIFS(Checklist!A:A,A10,Checklist!E:E,"Blocked") | F10: =COUNTIFS(Checklist!A:A,A10,Checklist!E:E,"N/A") | G10: =COUNTIFS(Checklist!A:A,A10,Checklist!E:E,"")
A11: 10. Buy | B11: =COUNTIF(Checklist!A:A,A11) | C11: =COUNTIFS(Checklist!A:A,A11,Checklist!E:E,"Pass") | D11: =COUNTIFS(Checklist!A:A,A11,Checklist!E:E,"Fail") | E11: =COUNTIFS(Checklist!A:A,A11,Checklist!E:E,"Blocked") | F11: =COUNTIFS(Checklist!A:A,A11,Checklist!E:E,"N/A") | G11: =COUNTIFS(Checklist!A:A,A11,Checklist!E:E,"")
A12: 11. Sell | B12: =COUNTIF(Checklist!A:A,A12) | C12: =COUNTIFS(Checklist!A:A,A12,Checklist!E:E,"Pass") | D12: =COUNTIFS(Checklist!A:A,A12,Checklist!E:E,"Fail") | E12: =COUNTIFS(Checklist!A:A,A12,Checklist!E:E,"Blocked") | F12: =COUNTIFS(Checklist!A:A,A12,Checklist!E:E,"N/A") | G12: =COUNTIFS(Checklist!A:A,A12,Checklist!E:E,"")
A13: 12. Swap | B13: =COUNTIF(Checklist!A:A,A13) | C13: =COUNTIFS(Checklist!A:A,A13,Checklist!E:E,"Pass") | D13: =COUNTIFS(Checklist!A:A,A13,Checklist!E:E,"Fail") | E13: =COUNTIFS(Checklist!A:A,A13,Checklist!E:E,"Blocked") | F13: =COUNTIFS(Checklist!A:A,A13,Checklist!E:E,"N/A") | G13: =COUNTIFS(Checklist!A:A,A13,Checklist!E:E,"")
... A26: 25. Crash Recovery | B26: =COUNTIF(Checklist!A:A,A26) | C26: =COUNTIFS(Checklist!A:A,A26,Checklist!E:E,"Pass") | D26: =COUNTIFS(Checklist!A:A,A26,Checklist!E:E,"Fail") | E26: =COUNTIFS(Checklist!A:A,A26,Checklist!E:E,"Blocked") | F26: =COUNTIFS(Checklist!A:A,A26,Checklist!E:E,"N/A") | G26: =COUNTIFS(Checklist!A:A,A26,Checklist!E:E,"")
A27: TOTAL | B27: =SUM(B2:B26) | C27: =SUM(C2:C26) | D27: =SUM(D2:D26) | E27: =SUM(E2:E26) | F27: =SUM(F2:F26) | G27: =SUM(G2:G26)
A29: Pass/Fail values allowed: Pass, Fail, Blocked, N/A
